modbus_tk/__init__.py
modbus_tk/defines.py
modbus_tk/exceptions.py
modbus_tk/hooks.py
modbus_tk/modbus.py
modbus_tk/modbus_rtu.py
modbus_tk/modbus_rtu_over_tcp.py
modbus_tk/modbus_tcp.py
modbus_tk/pymodbusclient.py
modbus_tk/simulator.py
modbus_tk/simulator_rpc_client.py
modbus_tk/utils.py
modbus_tk-1.1.3.dist-info/METADATA
modbus_tk-1.1.3.dist-info/WHEEL
modbus_tk-1.1.3.dist-info/top_level.txt
modbus_tk-1.1.3.dist-info/RECORD
