Metadata-Version: 2.1
Name: modbus-tk
Version: 1.1.3
Summary: Implementation of modbus protocol in python
Home-page: https://github.com/ljean/modbus-tk/
Author: Luc Jean
Author-email: luc.jean@gmail.com
Maintainer: Luc Jean
Maintainer-email: luc.jean@gmail.com
License: LGPL-2.1-or-later
Keywords: modbus,serial,tcp
Platform: Linux
Platform: Mac OS X
Platform: Win
Classifier: Development Status :: 5 - Production/Stable
Classifier: Environment :: Console
Classifier: Intended Audience :: Developers
Classifier: License :: OSI Approved :: GNU Library or Lesser General Public License (LGPL)
Classifier: Operating System :: OS Independent
Classifier: Programming Language :: Python
Classifier: Topic :: Communications
Classifier: Topic :: Software Development
